ArthimeticOp/ArthimeticOp.py
arthimeticop-0.0.1.dist-info/licenses/LICENSE.txt
arthimeticop-0.0.1.dist-info/METADATA
arthimeticop-0.0.1.dist-info/WHEEL
arthimeticop-0.0.1.dist-info/top_level.txt
arthimeticop-0.0.1.dist-info/RECORD
