Metadata-Version: 2.4
Name: ArthimeticOp
Version: 0.0.1
Summary: A small example package for addition sub multiply divide
Author-email: Example Author <author@example.com>
License-Expression: MIT
Project-URL: Homepage, https://github.com/postboxat18/ArthimeticOp.git
Classifier: Programming Language :: Python :: 3.11
Classifier: Operating System :: OS Independent
Requires-Python: >=3.9
License-File: LICENSE.txt
Dynamic: license-file
